<?xml version="1.0" encoding="utf-8"?>
<!--

     Copyright (C) 2022 xdroid & xyzprjkt

     Licensed under the Apache License, Version 2.0 (the "License");
     you may not use this file except in compliance with the License.
     You may obtain a copy of the License at

          http://www.apache.org/licenses/LICENSE-2.0

     Unless required by applicable law or agreed to in writing, software
     distributed under the License is distributed on an "AS IS" BASIS,
     WITHOUT WARRANTIES OR CONDITIONS OF ANY KIND, either express or implied.
     See the License for the specific language governing permissions and
     limitations under the License.
-->
<resources xmlns:xliff="urn:oasis:names:tc:xliff:document:1.2">
    <!-- Dashboard -->
    <string name="mnmlist_title">mnmlist</string>
    <string name="mnmlist_dashboard_title">什麼是 xdroid？</string>
    <string name="xd_tap_about">關於 xdroid</string>
    <string name="xd_tap_about_summary">點擊這裡了解更多關於xdroid的訊息</string>
    <string name="gestures_title">手勢</string>
    <string name="gestures_summary">雙擊手勢 • 系統導航</string>
    <string name="misc_title">雜項</string>
    <string name="misc_summary">進階重啟 • 震動</string>
    <string name="interfaces_title">系統介面</string>
    <string name="interfaces_summary"> 時鐘 • 電池 • 圖示 • 網路指示器</string>
    <string name="interfaces_style_title">系統樣式</string>
    <string name="interfaces_statusbar_title">狀態列</string>
    <string name="interfaces_battery_title">電量</string>
    <string name="buttons_title">按鍵</string>
    <string name="buttons_summary">音量鍵喚醒 • 播放控制</string>
    <string name="quicksettings_title">快速設定</string>
    <string name="quicksettings_summary">亮度滑塊 • 自動亮度</string>
    <string name="lockscreen_title">鎖定螢幕</string>
    <string name="lockscreen_summary">Always on display • 專輯封面 • 充電資訊</string>
    <string name="three_finger_gesture">滑動以擷取螢幕</string>
    <string name="three_finger_gesture_summary">三指下滑即可擷取螢幕畫面</string>
    <!-- Global Actions -->
    <string name="global_actions_advanced_reboot_title">啟用進階重啟</string>
    <string name="global_actions_advanced_reboot_summary">在電源選單中顯示 Recovery 和 Bootloader 選項</string>
    <!-- Display tap to wake custom summary -->
    <string name="tap_to_wake_summary_custom">在螢幕上任一處輕觸兩下即可喚醒或休眠裝置</string>
    <!-- Double Tap to Sleep Statusbar -->
    <string name="double_tap_sleep_gesture_title">輕觸即可休眠</string>
    <string name="double_tap_sleep_gesture_summary">輕觸兩下狀態列擊可讓裝置進入休眠</string>
    <!-- Statusbar Tuner -->
    <string name="statusbar_items_title">狀態列項目</string>
    <string name="statusbar_items_summary">啟用/禁用狀態列圖示</string>
    <!-- Volume rocker music control -->
    <string name="volume_button_music_control_title">播放控制</string>
    <string name="volume_button_music_control_summary">當螢幕關閉時，長按音量鍵即可切換曲目</string>
    <!-- Customization Categories/Fragment Titles -->
    <string name="clocksettings_title">時鐘設定</string>
    <string name="clocksettings_summary">狀態列時鐘設定</string>
    <string name="status_bar_clock_date_title">時鐘和日期</string>
    <string name="status_bar_clock_date_summary">自訂您的狀態列時鐘與日期</string>
    <string name="status_bar_clock_title">時鐘設置</string>
    <string name="status_bar_clock_show">顯示時鐘和日期</string>
    <string name="status_bar_clock_style_title">時鐘樣式</string>
    <string name="status_bar_clock_style_right">右側</string>
    <string name="status_bar_clock_style_center">置中</string>
    <string name="status_bar_clock_style_left">左側</string>
    <string name="status_bar_date_title">日期設置</string>
    <string name="status_bar_am_pm_title">上午/下午 樣式</string>
    <string name="status_bar_am_pm_info">24 小時格式已啟用</string>
    <string name="status_bar_am_pm_normal">正常</string>
    <string name="status_bar_am_pm_small">Small</string>
    <string name="status_bar_am_pm_hidden">隱藏 (預設)</string>
    <string name="clock_seconds_display">顯示秒數</string>
    <string name="clock_date_display">Date</string>
    <string name="clock_date_display_summary">Display custom date before the clock</string>
    <string name="clock_date_display_none">Don\'t show</string>
    <string name="clock_date_display_small">Small font size</string>
    <string name="clock_date_display_normal">Normal font size</string>
    <string name="clock_date_style">Date style</string>
    <string name="clock_date_style_normal">Normal</string>
    <string name="clock_date_style_lowercase">Lowercase</string>
    <string name="clock_date_style_uppercase">Uppercase</string>
    <string name="clock_date_format_custom">Custom java format</string>
    <string name="clock_date_format">Date format</string>
    <string name="clock_date_string_edittext_title">Must be in DateFormat eg. MM/dd/yy</string>
    <string name="clock_date_string_edittext_summary">Enter string</string>
    <string name="clock_date_right">Right of time</string>
    <string name="clock_date_left">Left of time</string>
    <string name="clock_date_position">日期位置</string>
    <!-- Torch Power button gestures -->
    <string name="torch_power_button_gesture_title">關閉螢幕時開關手電筒</string>
    <string name="torch_power_button_gesture_none">Disabled</string>
    <string name="torch_power_button_gesture_dt">Double tap power button (slower single tap response), Disables double power tap for camera.</string>
    <string name="torch_power_button_gesture_lp">Long press power button</string>
    <!-- Monet engine -->
    <string name="monet_engine_settings_title">Monet 引擎</string>
    <string name="monet_engine_settings_summary"> Adjust accent color, colorfulness and brightness</string>
    <string name="accurate_shades_title">Use accurate shades</string>
    <string name="use_wallpaper_color_title">Use wallpaper color</string>
    <string name="color_override_title">Accent color picker</string>
    <string name="color_override_summary">Choose a custom accent color to override the colors chosen by monet engine</string>
    <string name="chroma_factor_title">Colorfulness</string>
    <string name="linear_lightness_title">Use a custom lightness scale</string>
    <string name="white_luminance_title">亮度</string>
    <!-- 4G icon -->
    <string name="show_fourg_icon_title">4G 圖示</string>
    <string name="show_fourg_icon_summary">在訊號圖示上顯示 4G 而不是 LTE</string>
    <!-- Battery Styles -->
    <string name="battery_style_category_title">自訂電池圖示</string>
    <string name="battery_percent_title">電量百分比</string>
    <!-- Status bar - Battery -->
    <string name="status_bar_battery_style_title">電池樣式</string>
    <string name="status_bar_battery_style_icon_portrait">直立圖標 (預設)</string>
    <string name="status_bar_battery_style_circle">環狀</string>
    <string name="status_bar_battery_style_dotted_circle">環狀 (虛線)</string>
    <string name="status_bar_battery_style_filled_circle">圓圈 (實心)</string>
    <string name="status_bar_battery_style_text">文字</string>
    <string name="status_bar_battery_style_hidden">隱藏</string>
    <!-- Status bar - Battery percentage -->
    <string name="status_bar_battery_percentage_title">電量百分比</string>
    <string name="status_bar_battery_percentage_default">Hidden (default)</string>
    <string name="status_bar_battery_percentage_text_inside">Inside the icon</string>
    <string name="status_bar_battery_percentage_text_next">Next to the icon</string>
    <!-- Volume rocker wake -->
    <string name="volume_rocker_wake_title">音量鍵喚醒</string>
    <string name="volume_rocker_wake_summary">按下音量鍵即可喚醒裝置</string>
    <!-- Doze on double tap -->
    <string name="double_tap_title">Double tap</string>
    <string name="doze_double_tap_title">Double tap to check phone</string>
    <string name="doze_double_tap_summary">Pulse notifications by a double tap</string>
    <!-- Brightness slider -->
    <string name="qs_show_brightness_title">Brightness slider</string>
    <string name="qs_show_brightness_summary">Brightness slider visibility and settings</string>
    <string name="qs_brightness_position_bottom_title">Bottom brightness slider</string>
    <string name="qs_brightness_position_bottom_summary">Show the brightness slider on the bottom of QS</string>
    <string name="qs_show_auto_brightness_title">Auto brightness icon</string>
    <string name="qs_show_auto_brightness_summary">Show an auto brightness toggle near the brightness slider</string>
    <!-- Volume swap buttons -->
    <string name="swap_volume_buttons_title">Reorient</string>
    <string name="swap_volume_buttons_summary">Swap volume buttons when the screen is rotated</string>
    <!-- Misc gesture settings -->
    <string name="back_gesture_haptic_title">Haptic feedback</string>
    <string name="back_gesture_haptic_summary">Enable haptic tick effect on back gesture</string>
    <!-- Doze on charge -->
    <string name="doze_on_charge_title">Always on when charging</string>
    <string name="doze_on_charge_summary">Show doze screen all the time when charging</string>
    <!-- General strings -->
    <string name="default_string">Default</string>
    <string name="unit_seconds">Second(s)</string>
    <!-- Lockscreen media art -->
    <string name="lockscreen_media_art_category_title">Media art</string>
    <string name="keygaurd_media_art_title">Show media art</string>
    <string name="keygaurd_media_art_summary">Display media art as lockscreen background</string>
    <string name="lockscreen_media_blur_title">Media art blur level</string>
    <!-- Lockscreen battery info indicator  -->
    <string name="lockscreen_battery_info_title">Lockscreen charging info</string>
    <string name="lockscreen_battery_info_summary">Display negociated charger max current and voltage and battery temperature on lockscreen while charging</string>
    <!-- Statusbar net monitor -->
    <string name="statusbar_ntraffic">Network</string>
    <string name="network_traffic_state_title">Network speed</string>
    <string name="network_traffic_state_summary">Show network speed in the status bar</string>
    <string name="network_traffic_location_title">Location</string>
    <string name="network_traffic_statusbar">Statusbar</string>
    <string name="network_traffic_qs_header">QS header</string>
    <string name="network_traffic_mode_title">Display mode</string>
    <string name="network_traffic_dynamic">Dynamic</string>
    <string name="network_traffic_download">Download</string>
    <string name="network_traffic_upload">Upload</string>
    <string name="network_traffic_autohide_threshold_title">Auto-hide threshold</string>
    <string name="network_traffic_refresh_interval_title">Refresh interval</string>
    <!-- Keyguard force small clock -->
    <string name="lockscreen_small_clock_title">Force small clock</string>
    <string name="lockscreen_small_clock_summary">Don\'t switch to the big clock when there are no notifications</string>
    <!-- Brightness control -->
    <string name="status_bar_toggle_brightness">Brightness control</string>
    <string name="status_bar_toggle_brightness_summary">Adjust brightness by sliding across the status bar</string>
    <!-- Combined signal icons in status bar -->
    <string name="combined_status_bar_signal_icons">Combined signal icons</string>
    <string name="combined_status_bar_signal_icons_summary">Enable combined signal icons in status bar.\nRequires a SystemUI restart</string>
    <!-- Scramble pin -->
    <string name="unlock_scramble_pin_layout_title">Scramble layout</string>
    <string name="unlock_scramble_pin_layout_summary">Scramble PIN layout when unlocking device</string>
    <!-- Quick unlock -->
    <string name="unlock_quick_unlock_control_title">Quick unlock</string>
    <string name="unlock_quick_unlock_control_summary">Unlock automatically when the correct PIN/password is entered</string>
    <!-- Battery stats reset -->
    <string name="battery_stats_reset">Reset stats</string>
    <string name="battery_stats_message">Battery history stats are going to be reset</string>
    <!-- Android debugging as root -->
    <string name="adb_enable_root">Rooted debugging</string>
    <string name="adb_enable_summary_root">Allow running Android debugging as root</string>
    <!-- Fullscreen gestures -->
    <string name="other_controls_title">Other controls</string>
    <string name="fullscreen_gestures_title">Fullscreen gestures</string>
    <string name="fullscreen_gestures_summary">Hide navbar pill and keyboard space</string>
    <!-- Gesture navbar length -->
    <string name="gesture_navbar_length_title">Pill length</string>
    <string name="short_label">Short</string>
    <string name="long_label">Long</string>
</resources>
